frc/__init__.py
frc/_internal_utility.py
frc/deps_types.py
frc/frc_functions.py
frc/utility.py
frc-0.1.1.dist-info/LICENSE
frc-0.1.1.dist-info/METADATA
frc-0.1.1.dist-info/WHEEL
frc-0.1.1.dist-info/RECORD
