Metadata-Version: 2.1
Name: frc
Version: 0.1.1
Summary: Library for computing Fourier Ring Correlation (FRC) curves and using them to determine image resolution.
Author: Tip ten Brink
Author-email: T.M.tenBrink@student.tudelft.nl
Requires-Python: >=3.8,<3.13
Classifier: Programming Language :: Python :: 3
Classifier: Programming Language :: Python :: 3.8
Classifier: Programming Language :: Python :: 3.9
Classifier: Programming Language :: Python :: 3.10
Classifier: Programming Language :: Python :: 3.11
Classifier: Programming Language :: Python :: 3.12
Requires-Dist: diplib (>=3.1.0,<4.0.0)
Requires-Dist: numpy (>=1.18,<2.0) ; python_version < "3.12"
Requires-Dist: numpy (>=1.26,<2.0) ; python_version >= "3.12"
Requires-Dist: rustfrc (>=1.1.5,<2.0.0) ; python_version < "3.12"
Requires-Dist: rustfrc (>=1.1.5,<2.0.0) ; python_version >= "3.12"
Requires-Dist: scipy (>=1.11.2,<2.0.0) ; python_version >= "3.12"
Requires-Dist: scipy (>=1.3.2,<2.0.0) ; python_version < "3.12"
Project-URL: Source Code, https://github.com/tmtenbrink/frc
